{
	"genericName": "Tower Coordination",
	"description": "Royal Hubs, Guard Posts, and Silver Keeps within the Silver Tower's aura have a +15% increase in their fire rate and deal +3 Pierce Damage. Does not stack.",
	"cost": {"food": 0, "wood": 0, "stone": 300, "metal": 300},
	"requirements": {"all": [{"tech": "phase_city"}, {"civ": "lanayru"}]},
	"requirementsTooltip": "Unlocked with City.",
	"icon": "lanayru/tower_coordination.dds",
	"researchTime": 40,
	"tooltip": "Royal Hubs, Guard Posts, and Silver Keeps within the Silver Tower's aura have a +25% increase in their fire rate and deal +30% Pierce Damage. Does not stack.",
	"modifications": [],
	"affects": ["SilverTower"],
	"soundComplete": "interface/alarm/alarm_upgradearmory.xml"
}