{
	"genericName": "Frontier Roughness",
	"description": "",
	"cost": {"food": 300, "wood": 0, "stone": 0, "metal": 300},
	"requirements": {"all": [{"tech": "civ_choices/sheikah/choosehero_kohga"},{"tech": "phase_town"}, {"civ": "sheikah"}]},
	"requirementsTooltip": "Unlocked with Village.",
	"icon": "sheikah/kohga_frontier.dds",
	"researchTime": 40,
	"tooltip": "All non-creature, non-mechanical units gain additional HP.",
	"modifications": [{"value": "Health/Max", "multiply": 1.15}],
	"affects": ["Organic Infantry"],
	"hideIfTechnologyRequirementIsNotMet": "true",
	"soundComplete": "interface/alarm/alarm_upgradearmory.xml"
}
