<?xml version="1.0" encoding="utf-8"?>
<actor version="1">
  <castshadow/>
  <group>
    <variant file="HC_GDT/base_HC_gdt.xml">
      <mesh>units/fairy/fai_makuhoronA.dae</mesh>
	  <props>
        <prop actor="particle/fairy_leaves_spring.xml" attachpoint="root"/>
		<prop actor="particle/fairy_leaves_summer.xml" attachpoint="root"/>
		<prop actor="particle/fairy_leaves_autumnA.xml" attachpoint="root"/>
		<prop actor="particle/fairy_leaves_autumnB.xml" attachpoint="root"/>
		<prop actor="particle/fairy_field_maku.xml" attachpoint="root"/>
		<prop actor="units/fairy/fairy_makuhoron_face.xml" attachpoint="root"/>
		<prop actor="units/fairy/fairy_makufairies.xml" attachpoint="root"/>
	  </props>
      <textures><texture file="skeletal/fairy/fairy_makuhoronA.dds" name="baseTex"/></textures>
    </variant>
  </group>
  <group>
    <variant frequency="100" name="Idle"/>
    <variant name="Attack_Ranged">
	<props>
		<prop actor="particle/fairy_leaves_spring.xml" attachpoint="root"/>
		<prop actor="particle/fairy_leaves_summer.xml" attachpoint="root"/>
		<prop actor="particle/fairy_leaves_autumnA.xml" attachpoint="root"/>
		<prop actor="particle/fairy_leaves_autumnB.xml" attachpoint="root"/>
		<prop actor="particle/fairy_field_maku.xml" attachpoint="root"/>
		<prop actor="units/fairy/fairy_makuhoron_face.xml" attachpoint="root"/>
		<prop actor="units/fairy/fairy_makufairies.xml" attachpoint="root"/>
        <prop actor="particle/fairy_mist_summon.xml" attachpoint="root"/>
	  </props>
    </variant>
  </group>
  <group>
    <variant frequency="1" name="Idle"/>
    <variant file="HC_GDT/base_HC_makuhoron_att.xml"/>
    <variant name="Death">
      <props>
		<prop actor="units/fairy/fairy_makuhoron_face.xml" attachpoint="root"/>
		<prop actor="units/fairy/fairy_makufairies.xml" attachpoint="root"/>
      </props>
    </variant>
  </group>  
  <material>basic_trans.xml</material>
</actor>
