<Entity parent="structures/lizalfos/lizalfos_stables">
  <Identity>
    <RequiredTechnology>lizalfos_trinexx</RequiredTechnology>
  </Identity>
  <VisualActor>
    <Actor>structures/lizalfos/lizalfos_monstermoundB.xml</Actor>
  </VisualActor>
  <Researcher>
    <Technologies datatype="tokens">lizalfos/heatoise_perfectshell
    lizalfos/dodongosnake_diet

</Technologies>
  </Researcher>
  <Trainer>
    <BatchTimeModifier>0.8</BatchTimeModifier>
    <Entities datatype="tokens">units/lizalfos/{civ}_heatoise_b
      units/lizalfos/{civ}_dodongosnake_b</Entities>
  </Trainer>
</Entity>