{
	"genericName": "Ancestral Armor",
	"description": "Cavalry don the armor of the Gerudo Warlords.",
	"cost": {"metal": 400},
	"requirements": {"all": [ {"tech": "civ_choices/gerudo/choosehero_ganondorf"}, {"tech": "phase_city"}, {"civ": "gerudo"}]},
	"requirementsTooltip": "Requires Ganondorf and City Phase.",
	"icon": "tech_generic.dds",
	"researchTime": 50,
	"tooltip": "+25 Armor - Cavalry",
	"modifications": [{"value": "Resistance/Entity/Damage/Hack", "add": 25},
		{"value": "Resistance/Entity/Damage/Pierce", "add": 25},
		{"value": "Resistance/Entity/Damage/Crush", "add": 25}],
	"affects": ["Cavalry"],
	"hideIfTechnologyRequirementIsNotMet": "true",
	"soundComplete": "interface/alarm/alarm_upgradearmory.xml"
}
