<?xml version="1.0" encoding="utf-8"?>
<actor version="1">
  <castshadow/>
  <group>
    <variant file="HC_archer/base_HC_redeadknight.xml">
	<mesh>units/stalfos/sta_redeadknightA.dae</mesh>
	<textures><texture file="skeletal/stalfos/sta_mainB.dds" name="baseTex"/></textures>
	  <props>
      </props>
    </variant>
  </group>
  <group>
    <variant frequency="1" name="Idle"/>
    <variant file="HC_archer/base_HC_biped_death.xml">
      <props>
      </props>
    </variant>
  </group>
  <material>default.xml</material>
</actor>
