{
	"genericName": "Blacksmith's Tutelage",
	"description": "When he was a young Hylian Gulley's blacksmith of a father taugh him much in the way of metalworking. Gulley would later use these techniques to help improve Kokiri weaponry in order to combat the growing threats across Hyrule.",
	"cost": {"food": 0, "wood": 0, "stone": 250, "metal": 250},
	"requirements": {"all": [ {"tech": "civ_choices/kokiri/choosehero_gulley"}, {"tech": "phase_city"}, {"civ": "kokiri"}]},
	"requirementsTooltip": "You must select Gulley as your hero.",
	"icon": "kokiri/gulley_blacksmith.dds",
	"researchTime": 40,
	"tooltip": "+20% Melee Attack - All Infantry and Cavalry Melee Units",
	"modifications": [{"value": "Attack/Melee/Damage/Hack", "multiply": 1.2},
		{"value": "Attack/Melee/Damage/Pierce", "multiply": 1.2},
		{"value": "Attack/Melee/Damage/Crush", "multiply": 1.2}],
	"affects": ["Infantry Melee", "Cavalry Melee"],
	"soundComplete": "interface/alarm/alarm_upgradearmory.xml"
}
