{
	"genericName": "Ancestral Spirit",
	"description": "Wind Witches invoke their power to summon spirits of the dead as guardians.",
	"cost": {"food": 0, "wood": 0, "stone": 0, "metal": 300},
	"requirements": {"all": [{"tech": "phase_city"}, {"civ": "gerudo"}]},
	"requirementsTooltip": "Requires City Phase.",
	"icon": "gerudo/ancestral_spirit.dds",
	"researchTime": 40,
	"tooltip": " (+50% Armor vs. Magic - Wind Witch)",
	"modifications": [{"value": "Resistance/Entity/Damage/Magic", "add": 50},
		{"value": "Promotion/RequiredXp", "replace": 0}],
	"affects": ["WindWitch"],
	"soundComplete": "interface/alarm/alarm_upgradearmory.xml"
}